main.py
iflow_mcp_samge0_mcp_qqmusic_test_server-0.1.0.dist-info/METADATA
iflow_mcp_samge0_mcp_qqmusic_test_server-0.1.0.dist-info/WHEEL
iflow_mcp_samge0_mcp_qqmusic_test_server-0.1.0.dist-info/entry_points.txt
iflow_mcp_samge0_mcp_qqmusic_test_server-0.1.0.dist-info/top_level.txt
iflow_mcp_samge0_mcp_qqmusic_test_server-0.1.0.dist-info/RECORD
